{
  "strategyName": "Strong Volume Trend (Eearly Entry/Exit + JSON Export)",
  "symbolUniverse": "Nasdaq-100",
  "benchmark": "QQQ",
  "mode": "Long Only",
  "lastUpdate": "2026-04-09 23:57:43",
  "startingCapital": 40000,
  "backtestStartDate": "2019-01-02",
  "apr": 48.8937625530041,
  "profit": 456995.988678252,
  "profitPercent": 1142.48997169563,
  "riskReturnMetaScore": 51.7,
  "sharpeRatio": 1.39337207359686,
  "marRatio": 1.80411867261264,
  "recoveryFactor": 3.68766639777149,
  "maxDrawdown": -27.1011897915776,
  "avgReturnYear": 54.847713953119,
  "stdDeviationYear": 62.4829260330919,
  "avgBarsHeld": 92.5,
  "exposure": 77.9950566663061,
  "maximumExposure": 101.782608214869,
  "profitFactor": 11.2548253515836,
  "avgProfitPercent": 33.967866355285,
  "profitablePercent": 70.8333333333333,
  "positionCount": 48,
  "nsfPositionCount": 0,
  "maxMarginUsed": 1.01782608214869,
  "avgEntryEfficiencyPercent": 69.7617895176535,
  "avgExitEfficiencyPercent": -233.311314940667
}
