[
  {"symbol":"PLTR","action":"SELL","signalDate":"12/03/2026","entryPrice":0,"stopPrice":null,"targetPrice":null,"positionSizePercent":null,"signalName":"Sell At Market","orderType":"Market""signalStatus":"Staged""weigth":0.817049335857659, },
  {"symbol":"INTC","action":"SELL","signalDate":"12/03/2026","entryPrice":0,"stopPrice":null,"targetPrice":null,"positionSizePercent":null,"signalName":"Sell At Market","orderType":"Market""signalStatus":"Staged""weigth":0.547213164328826, },
  {"symbol":"NVDA","action":"SELL","signalDate":"12/03/2026","entryPrice":0,"stopPrice":null,"targetPrice":null,"positionSizePercent":null,"signalName":"Sell At Market","orderType":"Market""signalStatus":"Staged""weigth":0.395862800468826, },
  {"symbol":"TSLA","action":"SELL","signalDate":"12/03/2026","entryPrice":0,"stopPrice":null,"targetPrice":null,"positionSizePercent":null,"signalName":"Sell At Market","orderType":"Market""signalStatus":"Staged""weigth":0.38494341373016, }
]
